odoo10_addon_account_fiscal_position_rule_sale-10.0.1.0.0.99.dev5-py2.7-nspkg.pth
odoo/addons/account_fiscal_position_rule_sale/README.rst
odoo/addons/account_fiscal_position_rule_sale/__init__.py
odoo/addons/account_fiscal_position_rule_sale/__manifest__.py
odoo/addons/account_fiscal_position_rule_sale/i18n/account_fiscal_position_rule_sale.pot
odoo/addons/account_fiscal_position_rule_sale/i18n/en_US.po
odoo/addons/account_fiscal_position_rule_sale/i18n/es.po
odoo/addons/account_fiscal_position_rule_sale/i18n/hu.po
odoo/addons/account_fiscal_position_rule_sale/i18n/pt_BR.po
odoo/addons/account_fiscal_position_rule_sale/i18n/sl.po
odoo/addons/account_fiscal_position_rule_sale/models/__init__.py
odoo/addons/account_fiscal_position_rule_sale/models/sale.py
odoo/addons/account_fiscal_position_rule_sale/security/ir.model.access.csv
odoo/addons/account_fiscal_position_rule_sale/static/description/icon.png
odoo/addons/account_fiscal_position_rule_sale/test/account_fiscal_position_rule_sale.yml
odoo10_addon_account_fiscal_position_rule_sale-10.0.1.0.0.99.dev5.dist-info/METADATA
odoo10_addon_account_fiscal_position_rule_sale-10.0.1.0.0.99.dev5.dist-info/RECORD
odoo10_addon_account_fiscal_position_rule_sale-10.0.1.0.0.99.dev5.dist-info/WHEEL
odoo10_addon_account_fiscal_position_rule_sale-10.0.1.0.0.99.dev5.dist-info/namespace_packages.txt
odoo10_addon_account_fiscal_position_rule_sale-10.0.1.0.0.99.dev5.dist-info/top_level.txt
